Metadata-Version: 1.0
Name: matrix-mania
Version: 0.1
Summary: Basic Matrix Operations
Home-page: UNKNOWN
Author: Grant Gasser
Author-email: glgasser@gmail.com
License: UNKNOWN
Platform: UNKNOWN
